IRVLUTDDoorHandleDataset/__init__.py
IRVLUTDDoorHandleDataset/dataset.py
IRVLUTDDoorHandleDataset-1.0.4.dist-info/LICENSE
IRVLUTDDoorHandleDataset-1.0.4.dist-info/METADATA
IRVLUTDDoorHandleDataset-1.0.4.dist-info/WHEEL
IRVLUTDDoorHandleDataset-1.0.4.dist-info/top_level.txt
IRVLUTDDoorHandleDataset-1.0.4.dist-info/RECORD
