Metadata-Version: 2.1
Name: IRVLUTDDoorHandleDataset
Version: 1.0.4
Summary: PyTorch dataset loader for IRVLUTD Door Handle dataset
Home-page: https://irvlutd.github.io/iTeach
Author: Jishnu Jaykumar P
Author-email: jishnu.p@utdallas.edu
Classifier: Programming Language :: Python :: 3
Classifier: License :: OSI Approved :: MIT License
Classifier: Operating System :: OS Independent
Requires-Python: >=3.6
License-File: LICENSE
Requires-Dist: torch
Requires-Dist: Pillow
Requires-Dist: numpy
